grapl_ipc_analyzer_plugin/__init__.py
grapl_ipc_analyzer_plugin/ipc_node.py
grapl_ipc_analyzer_plugin/py.typed
grapl_ipc_analyzer_plugin-0.0.3.dist-info/DESCRIPTION.rst
grapl_ipc_analyzer_plugin-0.0.3.dist-info/METADATA
grapl_ipc_analyzer_plugin-0.0.3.dist-info/RECORD
grapl_ipc_analyzer_plugin-0.0.3.dist-info/WHEEL
grapl_ipc_analyzer_plugin-0.0.3.dist-info/metadata.json
grapl_ipc_analyzer_plugin-0.0.3.dist-info/top_level.txt
