Metadata-Version: 2.0
Name: grapl-ipc-analyzer-plugin
Version: 0.0.3
Summary: Library for Grapl Analyzers
Home-page: https://github.com/insanitybit/grapl-ipc-plugin/
Author: insanitybit
Author-email: insanitybit@gmail.com
License: MIT
Platform: UNKNOWN
Classifier: License :: OSI Approved :: MIT License
Classifier: Programming Language :: Python :: 3
Classifier: Programming Language :: Python :: 3.7
Requires-Dist: pydgraph
